<?xml version="1.0" encoding="UTF-8"?>
<page login-required="true"
 xmlns="http://jboss.org/schema/seam/pages"
 xmlns:xsi="http://www.w3.org/2001/XMLSchema-instance" xsi:schemaLocation="http://jboss.org/schema/seam/pages http://jboss.org/schema/seam/pages-2.3.xsd">

 <param name="firstResult" value="#{unitDeathList.firstResult}"/>
 <param name="sort" value="#{unitDeathList.orderColumn}"/>
 <param name="dir" value="#{unitDeathList.orderDirection}"/>
 <param name="logic" value="#{unitDeathList.restrictionLogicOperator}"/>

 <param name="from"/>
 <param name="cementeryName" value="#{unitDeathList.cementeryName}"/>
 <param name="sectionName" value="#{unitDeathList.sectionName}"/>
 <param name="deceasedCriteria" value="#{unitDeathList.deceasedCriteria}"/>
 <param name="debtorCriteria" value="#{unitDeathList.debtorCriteria}"/>
 <param name="dateOfDeath" value="#{unitDeathList.dateOfDeath}" converterId="org.jboss.seam.ui.DateTimeConverter"/>
 <param name="unitStatus" value="#{unitDeathList.unitStatus}"/>
 <param name="unitType" value="#{unitDeathList.unitType}"/>
</page>
